InsideForest/__init__.py
InsideForest/ab_testing.py
InsideForest/cluster_selector.py
InsideForest/descrip.py
InsideForest/inside_forest.py
InsideForest/labels.py
InsideForest/legacy_select_clusters.py
InsideForest/metadata.py
InsideForest/models.py
InsideForest/regions.py
InsideForest/trees.py
experiments/__init__.py
experiments/ab_test_rule_extraction.py
experiments/benchmark.py
experiments/benchmark_get_rangos.py
experiments/rf_param_benchmark.py
experiments/run_select_clusters_benchmark.py
experiments/select_clusters_ab_benchmark.py
experiments/select_clusters_hyperparam.py
experiments/summary_benchmark.py
insideforest-0.3.9.dist-info/licenses/LICENSE
insideforest-0.3.9.dist-info/METADATA
insideforest-0.3.9.dist-info/WHEEL
insideforest-0.3.9.dist-info/top_level.txt
insideforest-0.3.9.dist-info/RECORD
