Metadata-Version: 2.4
Name: InsideForest
Version: 0.3.9
Summary: A comprehensive library for describing and analyzing data insights via AI
Home-page: https://github.com/jcval94/InsideForest.git
Author: Jose Carlos Del Valle
License: MIT
License-File: LICENSE
Dynamic: author
Dynamic: description
Dynamic: description-content-type
Dynamic: home-page
Dynamic: license
Dynamic: license-file
Dynamic: summary
